flask-stubs/METADATA.toml
flask-stubs/__init__.pyi
flask-stubs/app.pyi
flask-stubs/blueprints.pyi
flask-stubs/cli.pyi
flask-stubs/config.pyi
flask-stubs/ctx.pyi
flask-stubs/debughelpers.pyi
flask-stubs/globals.pyi
flask-stubs/helpers.pyi
flask-stubs/logging.pyi
flask-stubs/sessions.pyi
flask-stubs/signals.pyi
flask-stubs/templating.pyi
flask-stubs/testing.pyi
flask-stubs/views.pyi
flask-stubs/wrappers.pyi
flask-stubs/json/__init__.pyi
flask-stubs/json/tag.pyi
types_Flask-1.1.6.dist-info/METADATA
types_Flask-1.1.6.dist-info/WHEEL
types_Flask-1.1.6.dist-info/top_level.txt
types_Flask-1.1.6.dist-info/RECORD
