Metadata-Version: 2.1
Name: types-Flask
Version: 1.1.6
Summary: Typing stubs for Flask
Home-page: https://github.com/python/typeshed
License: Apache-2.0 license
Platform: UNKNOWN
Classifier: License :: OSI Approved :: Apache Software License
Classifier: Typing :: Typed
